pytest_honey.py
pytest_honey-0.2.0.dist-info/LICENSE
pytest_honey-0.2.0.dist-info/METADATA
pytest_honey-0.2.0.dist-info/WHEEL
pytest_honey-0.2.0.dist-info/entry_points.txt
pytest_honey-0.2.0.dist-info/top_level.txt
pytest_honey-0.2.0.dist-info/RECORD
